django_mom/__init__.py
django_mom/settings.py
django_mom/management/__init__.py
django_mom/management/commands/__init__.py
django_mom/management/commands/mom.py
django_mom-0.0.6.dist-info/LICENSE
django_mom-0.0.6.dist-info/METADATA
django_mom-0.0.6.dist-info/WHEEL
django_mom-0.0.6.dist-info/top_level.txt
django_mom-0.0.6.dist-info/RECORD
