Metadata-Version: 2.1
Name: django-mom
Version: 0.0.6
Summary: Maps plain text data to a model, creating, updating, or removing it as it changes
Home-page: https://github.com/velitasali/django-mom
Author: Veli Tasalı
Author-email: me@velitasali.com
License: MIT
Project-URL: Source, https://github.com/velitasali/django-mom/
Project-URL: Tracker, https://github.com/velitasali/django-mom/issues/
Platform: UNKNOWN
Classifier: Development Status :: 3 - Alpha
Classifier: Framework :: Django :: 2.2
Classifier: Framework :: Django :: 3.0
Classifier: Framework :: Django :: 3.1
Classifier: Topic :: Database :: Front-Ends
Requires-Python: >=3.6
License-File: LICENSE
Requires-Dist: django (>=3.2.3)
Requires-Dist: PyYAML (>=5.4.1)
